gitsubdirs.py
setup.py
git_subdirs.egg-info/PKG-INFO
git_subdirs.egg-info/SOURCES.txt
git_subdirs.egg-info/dependency_links.txt
git_subdirs.egg-info/entry_points.txt
git_subdirs.egg-info/top_level.txt