Metadata-Version: 1.0
Name: git-subdirs
Version: 0.1
Summary: Small wrapper for performing git commands on nested repositories in subdirectories
Home-page: https://github.com/vlasovskikh/git-subdirs
Author: Andrey Vlasovskikh
Author-email: andrey.vlasovskikh@gmail.com
License: MIT
Platform: UNKNOWN
